pydate/__init__.py
pydate/__main__.py
pydate/types.py
pydate/add/__init__.py
pydate/add/add.py
pydate/add/test.py
pydate/add_days/__init__.py
pydate/add_days/add_days.py
pydate/add_days/test.py
pydate/add_hours/__init__.py
pydate/add_hours/add_hours.py
pydate/add_hours/test.py
pydate/add_milliseconds/__init__.py
pydate/add_milliseconds/add_milliseconds.py
pydate/add_milliseconds/test.py
pydate/add_months/__init__.py
pydate/add_months/add_months.py
pydate/add_months/test.py
pydate/add_weeks/__init__.py
pydate/add_weeks/add_weeks.py
pydate/add_weeks/test.py
pydate/add_years/__init__.py
pydate/add_years/add_years.py
pydate/add_years/test.py
pydate/closest_to/__init__.py
pydate/closest_to/closest_to.py
pydate/closest_to/test.py
pydate/is_after/__init__.py
pydate/is_after/is_after.py
pydate/is_after/test.py
pydate/is_before/__init__.py
pydate/is_before/is_before.py
pydate/is_before/test.py
pydate/is_date/__init__.py
pydate/is_date/is_date.py
pydate/is_date/test.py
pydate/is_equal/__init__.py
pydate/is_equal/is_equal.py
pydate/is_equal/test.py
pydate/is_exists/__init__.py
pydate/is_exists/is_exists.py
pydate/is_exists/test.py
pydate/is_first_day_of_month/__init__.py
pydate/is_first_day_of_month/is_first_day_of_month.py
pydate/is_first_day_of_month/test.py
pydate/is_friday/__init__.py
pydate/is_friday/is_friday.py
pydate/is_friday/test.py
pydate/is_last_day_of_month/__init__.py
pydate/is_last_day_of_month/is_last_day_of_month.py
pydate/is_last_day_of_month/test.py
pydate/is_leap_year/__init__.py
pydate/is_leap_year/is_leap_year.py
pydate/is_leap_year/test.py
pydate/is_monday/__init__.py
pydate/is_monday/is_monday.py
pydate/is_monday/test.py
pydate/is_same_day/__init__.py
pydate/is_same_day/is_same_day.py
pydate/is_same_day/test.py
pydate/is_same_hour/__init__.py
pydate/is_same_hour/is_same_hour.py
pydate/is_same_hour/test.py
pydate/is_same_minute/__init__.py
pydate/is_same_minute/is_same_minute.py
pydate/is_same_minute/test.py
pydate/is_same_month/__init__.py
pydate_fns-0.1.1.dist-info/LICENSE.txt
pydate_fns-0.1.1.dist-info/METADATA
pydate_fns-0.1.1.dist-info/WHEEL
pydate_fns-0.1.1.dist-info/top_level.txt
pydate_fns-0.1.1.dist-info/RECORD
